MANIFEST.in
README.md
setup.py
django_singleton.egg-info/PKG-INFO
django_singleton.egg-info/SOURCES.txt
django_singleton.egg-info/dependency_links.txt
django_singleton.egg-info/not-zip-safe
django_singleton.egg-info/top_level.txt
singleton_models/__init__.py
singleton_models/admin.py
singleton_models/models.py
singleton_models/templates/admin/singleton_models/change_form.html