Metadata-Version: 1.1
Name: django-singleton
Version: 0.1.8
Summary: Reusable singleton models for Django
Home-page: https://github.com/defbyte/django-singleton
Author: Chris Davis
Author-email: defbyte@gmail.com
License: UNKNOWN
Platform: UNKNOWN
Classifier: Development Status :: 4 - Beta
Classifier: Environment :: Web Environment
Classifier: Intended Audience :: Developers
Classifier: License :: OSI Approved :: BSD License
Classifier: Operating System :: OS Independent
Classifier: Programming Language :: Python
Classifier: Framework :: Django
